{
  "schemaVersion": "1.0",
  "generatedAt": "2026-02-15T00:00:00.000Z",
  "sourceVersion": "v20260215",
  "rowCount": 51,
  "columns": [
    "slug",
    "state",
    "avgRateCentsPerKwh",
    "nationalAverage",
    "differencePercent",
    "momentumSignal",
    "generatedAt",
    "sourceVersion"
  ],
  "data": [
    {
      "slug": "alabama",
      "state": "Alabama",
      "avgRateCentsPerKwh": 16.18,
      "nationalAverage": 18.24,
      "differencePercent": -11.3,
      "momentumSignal": "rising",
      "generatedAt": "2026-02-15T00:00:00.000Z",
      "sourceVersion": "v20260215"
    },
    {
      "slug": "alaska",
      "state": "Alaska",
      "avgRateCentsPerKwh": 25.79,
      "nationalAverage": 18.24,
      "differencePercent": 41.4,
      "momentumSignal": "rising",
      "generatedAt": "2026-02-15T00:00:00.000Z",
      "sourceVersion": "v20260215"
    },
    {
      "slug": "arizona",
      "state": "Arizona",
      "avgRateCentsPerKwh": 16.03,
      "nationalAverage": 18.24,
      "differencePercent": -12.1,
      "momentumSignal": "rising",
      "generatedAt": "2026-02-15T00:00:00.000Z",
      "sourceVersion": "v20260215"
    },
    {
      "slug": "arkansas",
      "state": "Arkansas",
      "avgRateCentsPerKwh": 12.73,
      "nationalAverage": 18.24,
      "differencePercent": -30.2,
      "momentumSignal": "accelerating",
      "generatedAt": "2026-02-15T00:00:00.000Z",
      "sourceVersion": "v20260215"
    },
    {
      "slug": "california",
      "state": "California",
      "avgRateCentsPerKwh": 33.22,
      "nationalAverage": 18.24,
      "differencePercent": 82.1,
      "momentumSignal": "accelerating",
      "generatedAt": "2026-02-15T00:00:00.000Z",
      "sourceVersion": "v20260215"
    },
    {
      "slug": "colorado",
      "state": "Colorado",
      "avgRateCentsPerKwh": 16.79,
      "nationalAverage": 18.24,
      "differencePercent": -7.9,
      "momentumSignal": "accelerating",
      "generatedAt": "2026-02-15T00:00:00.000Z",
      "sourceVersion": "v20260215"
    },
    {
      "slug": "connecticut",
      "state": "Connecticut",
      "avgRateCentsPerKwh": 30.77,
      "nationalAverage": 18.24,
      "differencePercent": 68.7,
      "momentumSignal": "falling",
      "generatedAt": "2026-02-15T00:00:00.000Z",
      "sourceVersion": "v20260215"
    },
    {
      "slug": "delaware",
      "state": "Delaware",
      "avgRateCentsPerKwh": 16.27,
      "nationalAverage": 18.24,
      "differencePercent": -10.8,
      "momentumSignal": "accelerating",
      "generatedAt": "2026-02-15T00:00:00.000Z",
      "sourceVersion": "v20260215"
    },
    {
      "slug": "florida",
      "state": "Florida",
      "avgRateCentsPerKwh": 15.8,
      "nationalAverage": 18.24,
      "differencePercent": -13.4,
      "momentumSignal": "accelerating",
      "generatedAt": "2026-02-15T00:00:00.000Z",
      "sourceVersion": "v20260215"
    },
    {
      "slug": "georgia",
      "state": "Georgia",
      "avgRateCentsPerKwh": 14.13,
      "nationalAverage": 18.24,
      "differencePercent": -22.5,
      "momentumSignal": "rising",
      "generatedAt": "2026-02-15T00:00:00.000Z",
      "sourceVersion": "v20260215"
    },
    {
      "slug": "hawaii",
      "state": "Hawaii",
      "avgRateCentsPerKwh": 43,
      "nationalAverage": 18.24,
      "differencePercent": 135.7,
      "momentumSignal": "stable",
      "generatedAt": "2026-02-15T00:00:00.000Z",
      "sourceVersion": "v20260215"
    },
    {
      "slug": "idaho",
      "state": "Idaho",
      "avgRateCentsPerKwh": 12.63,
      "nationalAverage": 18.24,
      "differencePercent": -30.8,
      "momentumSignal": "accelerating",
      "generatedAt": "2026-02-15T00:00:00.000Z",
      "sourceVersion": "v20260215"
    },
    {
      "slug": "illinois",
      "state": "Illinois",
      "avgRateCentsPerKwh": 17.83,
      "nationalAverage": 18.24,
      "differencePercent": -2.2,
      "momentumSignal": "accelerating",
      "generatedAt": "2026-02-15T00:00:00.000Z",
      "sourceVersion": "v20260215"
    },
    {
      "slug": "indiana",
      "state": "Indiana",
      "avgRateCentsPerKwh": 16.06,
      "nationalAverage": 18.24,
      "differencePercent": -12,
      "momentumSignal": "accelerating",
      "generatedAt": "2026-02-15T00:00:00.000Z",
      "sourceVersion": "v20260215"
    },
    {
      "slug": "iowa",
      "state": "Iowa",
      "avgRateCentsPerKwh": 12.74,
      "nationalAverage": 18.24,
      "differencePercent": -30.2,
      "momentumSignal": "accelerating",
      "generatedAt": "2026-02-15T00:00:00.000Z",
      "sourceVersion": "v20260215"
    },
    {
      "slug": "kansas",
      "state": "Kansas",
      "avgRateCentsPerKwh": 15.11,
      "nationalAverage": 18.24,
      "differencePercent": -17.2,
      "momentumSignal": "accelerating",
      "generatedAt": "2026-02-15T00:00:00.000Z",
      "sourceVersion": "v20260215"
    },
    {
      "slug": "kentucky",
      "state": "Kentucky",
      "avgRateCentsPerKwh": 13.42,
      "nationalAverage": 18.24,
      "differencePercent": -26.4,
      "momentumSignal": "rising",
      "generatedAt": "2026-02-15T00:00:00.000Z",
      "sourceVersion": "v20260215"
    },
    {
      "slug": "louisiana",
      "state": "Louisiana",
      "avgRateCentsPerKwh": 12.87,
      "nationalAverage": 18.24,
      "differencePercent": -29.4,
      "momentumSignal": "accelerating",
      "generatedAt": "2026-02-15T00:00:00.000Z",
      "sourceVersion": "v20260215"
    },
    {
      "slug": "maine",
      "state": "Maine",
      "avgRateCentsPerKwh": 32.17,
      "nationalAverage": 18.24,
      "differencePercent": 76.4,
      "momentumSignal": "accelerating",
      "generatedAt": "2026-02-15T00:00:00.000Z",
      "sourceVersion": "v20260215"
    },
    {
      "slug": "maryland",
      "state": "Maryland",
      "avgRateCentsPerKwh": 20.08,
      "nationalAverage": 18.24,
      "differencePercent": 10.1,
      "momentumSignal": "accelerating",
      "generatedAt": "2026-02-15T00:00:00.000Z",
      "sourceVersion": "v20260215"
    },
    {
      "slug": "massachusetts",
      "state": "Massachusetts",
      "avgRateCentsPerKwh": 30.46,
      "nationalAverage": 18.24,
      "differencePercent": 67,
      "momentumSignal": "stable",
      "generatedAt": "2026-02-15T00:00:00.000Z",
      "sourceVersion": "v20260215"
    },
    {
      "slug": "michigan",
      "state": "Michigan",
      "avgRateCentsPerKwh": 20,
      "nationalAverage": 18.24,
      "differencePercent": 9.6,
      "momentumSignal": "accelerating",
      "generatedAt": "2026-02-15T00:00:00.000Z",
      "sourceVersion": "v20260215"
    },
    {
      "slug": "minnesota",
      "state": "Minnesota",
      "avgRateCentsPerKwh": 15.39,
      "nationalAverage": 18.24,
      "differencePercent": -15.6,
      "momentumSignal": "accelerating",
      "generatedAt": "2026-02-15T00:00:00.000Z",
      "sourceVersion": "v20260215"
    },
    {
      "slug": "mississippi",
      "state": "Mississippi",
      "avgRateCentsPerKwh": 14.72,
      "nationalAverage": 18.24,
      "differencePercent": -19.3,
      "momentumSignal": "accelerating",
      "generatedAt": "2026-02-15T00:00:00.000Z",
      "sourceVersion": "v20260215"
    },
    {
      "slug": "missouri",
      "state": "Missouri",
      "avgRateCentsPerKwh": 12.17,
      "nationalAverage": 18.24,
      "differencePercent": -33.3,
      "momentumSignal": "accelerating",
      "generatedAt": "2026-02-15T00:00:00.000Z",
      "sourceVersion": "v20260215"
    },
    {
      "slug": "montana",
      "state": "Montana",
      "avgRateCentsPerKwh": 13.33,
      "nationalAverage": 18.24,
      "differencePercent": -26.9,
      "momentumSignal": "accelerating",
      "generatedAt": "2026-02-15T00:00:00.000Z",
      "sourceVersion": "v20260215"
    },
    {
      "slug": "nebraska",
      "state": "Nebraska",
      "avgRateCentsPerKwh": 11.79,
      "nationalAverage": 18.24,
      "differencePercent": -35.4,
      "momentumSignal": "accelerating",
      "generatedAt": "2026-02-15T00:00:00.000Z",
      "sourceVersion": "v20260215"
    },
    {
      "slug": "nevada",
      "state": "Nevada",
      "avgRateCentsPerKwh": 14.38,
      "nationalAverage": 18.24,
      "differencePercent": -21.2,
      "momentumSignal": "stable",
      "generatedAt": "2026-02-15T00:00:00.000Z",
      "sourceVersion": "v20260215"
    },
    {
      "slug": "new-hampshire",
      "state": "New Hampshire",
      "avgRateCentsPerKwh": 26.52,
      "nationalAverage": 18.24,
      "differencePercent": 45.4,
      "momentumSignal": "accelerating",
      "generatedAt": "2026-02-15T00:00:00.000Z",
      "sourceVersion": "v20260215"
    },
    {
      "slug": "new-jersey",
      "state": "New Jersey",
      "avgRateCentsPerKwh": 23.12,
      "nationalAverage": 18.24,
      "differencePercent": 26.8,
      "momentumSignal": "accelerating",
      "generatedAt": "2026-02-15T00:00:00.000Z",
      "sourceVersion": "v20260215"
    },
    {
      "slug": "new-mexico",
      "state": "New Mexico",
      "avgRateCentsPerKwh": 15.07,
      "nationalAverage": 18.24,
      "differencePercent": -17.4,
      "momentumSignal": "rising",
      "generatedAt": "2026-02-15T00:00:00.000Z",
      "sourceVersion": "v20260215"
    },
    {
      "slug": "new-york",
      "state": "New York",
      "avgRateCentsPerKwh": 29.99,
      "nationalAverage": 18.24,
      "differencePercent": 64.4,
      "momentumSignal": "accelerating",
      "generatedAt": "2026-02-15T00:00:00.000Z",
      "sourceVersion": "v20260215"
    },
    {
      "slug": "north-carolina",
      "state": "North Carolina",
      "avgRateCentsPerKwh": 14.64,
      "nationalAverage": 18.24,
      "differencePercent": -19.7,
      "momentumSignal": "accelerating",
      "generatedAt": "2026-02-15T00:00:00.000Z",
      "sourceVersion": "v20260215"
    },
    {
      "slug": "north-dakota",
      "state": "North Dakota",
      "avgRateCentsPerKwh": 11.64,
      "nationalAverage": 18.24,
      "differencePercent": -36.2,
      "momentumSignal": "accelerating",
      "generatedAt": "2026-02-15T00:00:00.000Z",
      "sourceVersion": "v20260215"
    },
    {
      "slug": "ohio",
      "state": "Ohio",
      "avgRateCentsPerKwh": 17.52,
      "nationalAverage": 18.24,
      "differencePercent": -3.9,
      "momentumSignal": "accelerating",
      "generatedAt": "2026-02-15T00:00:00.000Z",
      "sourceVersion": "v20260215"
    },
    {
      "slug": "oklahoma",
      "state": "Oklahoma",
      "avgRateCentsPerKwh": 12.89,
      "nationalAverage": 18.24,
      "differencePercent": -29.3,
      "momentumSignal": "accelerating",
      "generatedAt": "2026-02-15T00:00:00.000Z",
      "sourceVersion": "v20260215"
    },
    {
      "slug": "oregon",
      "state": "Oregon",
      "avgRateCentsPerKwh": 14.64,
      "nationalAverage": 18.24,
      "differencePercent": -19.7,
      "momentumSignal": "stable",
      "generatedAt": "2026-02-15T00:00:00.000Z",
      "sourceVersion": "v20260215"
    },
    {
      "slug": "pennsylvania",
      "state": "Pennsylvania",
      "avgRateCentsPerKwh": 20.3,
      "nationalAverage": 18.24,
      "differencePercent": 11.3,
      "momentumSignal": "accelerating",
      "generatedAt": "2026-02-15T00:00:00.000Z",
      "sourceVersion": "v20260215"
    },
    {
      "slug": "rhode-island",
      "state": "Rhode Island",
      "avgRateCentsPerKwh": 29.45,
      "nationalAverage": 18.24,
      "differencePercent": 61.5,
      "momentumSignal": "falling",
      "generatedAt": "2026-02-15T00:00:00.000Z",
      "sourceVersion": "v20260215"
    },
    {
      "slug": "south-carolina",
      "state": "South Carolina",
      "avgRateCentsPerKwh": 16.15,
      "nationalAverage": 18.24,
      "differencePercent": -11.5,
      "momentumSignal": "accelerating",
      "generatedAt": "2026-02-15T00:00:00.000Z",
      "sourceVersion": "v20260215"
    },
    {
      "slug": "south-dakota",
      "state": "South Dakota",
      "avgRateCentsPerKwh": 13.24,
      "nationalAverage": 18.24,
      "differencePercent": -27.4,
      "momentumSignal": "accelerating",
      "generatedAt": "2026-02-15T00:00:00.000Z",
      "sourceVersion": "v20260215"
    },
    {
      "slug": "tennessee",
      "state": "Tennessee",
      "avgRateCentsPerKwh": 12.82,
      "nationalAverage": 18.24,
      "differencePercent": -29.7,
      "momentumSignal": "rising",
      "generatedAt": "2026-02-15T00:00:00.000Z",
      "sourceVersion": "v20260215"
    },
    {
      "slug": "texas",
      "state": "Texas",
      "avgRateCentsPerKwh": 15.41,
      "nationalAverage": 18.24,
      "differencePercent": -15.5,
      "momentumSignal": "rising",
      "generatedAt": "2026-02-15T00:00:00.000Z",
      "sourceVersion": "v20260215"
    },
    {
      "slug": "utah",
      "state": "Utah",
      "avgRateCentsPerKwh": 13.33,
      "nationalAverage": 18.24,
      "differencePercent": -26.9,
      "momentumSignal": "rising",
      "generatedAt": "2026-02-15T00:00:00.000Z",
      "sourceVersion": "v20260215"
    },
    {
      "slug": "vermont",
      "state": "Vermont",
      "avgRateCentsPerKwh": 23.27,
      "nationalAverage": 18.24,
      "differencePercent": 27.6,
      "momentumSignal": "rising",
      "generatedAt": "2026-02-15T00:00:00.000Z",
      "sourceVersion": "v20260215"
    },
    {
      "slug": "virginia",
      "state": "Virginia",
      "avgRateCentsPerKwh": 15.96,
      "nationalAverage": 18.24,
      "differencePercent": -12.5,
      "momentumSignal": "accelerating",
      "generatedAt": "2026-02-15T00:00:00.000Z",
      "sourceVersion": "v20260215"
    },
    {
      "slug": "washington",
      "state": "Washington",
      "avgRateCentsPerKwh": 14.11,
      "nationalAverage": 18.24,
      "differencePercent": -22.6,
      "momentumSignal": "accelerating",
      "generatedAt": "2026-02-15T00:00:00.000Z",
      "sourceVersion": "v20260215"
    },
    {
      "slug": "west-virginia",
      "state": "West Virginia",
      "avgRateCentsPerKwh": 14.41,
      "nationalAverage": 18.24,
      "differencePercent": -21,
      "momentumSignal": "falling",
      "generatedAt": "2026-02-15T00:00:00.000Z",
      "sourceVersion": "v20260215"
    },
    {
      "slug": "wisconsin",
      "state": "Wisconsin",
      "avgRateCentsPerKwh": 18.74,
      "nationalAverage": 18.24,
      "differencePercent": 2.7,
      "momentumSignal": "accelerating",
      "generatedAt": "2026-02-15T00:00:00.000Z",
      "sourceVersion": "v20260215"
    },
    {
      "slug": "wyoming",
      "state": "Wyoming",
      "avgRateCentsPerKwh": 13.04,
      "nationalAverage": 18.24,
      "differencePercent": -28.5,
      "momentumSignal": "accelerating",
      "generatedAt": "2026-02-15T00:00:00.000Z",
      "sourceVersion": "v20260215"
    },
    {
      "slug": "district-of-columbia",
      "state": "District of Columbia",
      "avgRateCentsPerKwh": null,
      "nationalAverage": 18.24,
      "differencePercent": 0,
      "momentumSignal": "accelerating",
      "generatedAt": "2026-02-15T00:00:00.000Z",
      "sourceVersion": "v20260215"
    }
  ]
}
